{
  "version": 1,
  "description": "Canary regression suite — siti noti funzionanti con AdOff",
  "canaries": [
    {"domain": "repubblica.it", "category": "news", "site_type": "article", "expected_leaks": 0},
    {"domain": "ansa.it", "category": "news", "site_type": "article", "expected_leaks": 0},
    {"domain": "bbc.com", "category": "news", "site_type": "article", "expected_leaks": 0},
    {"domain": "amazon.it", "category": "ecommerce", "site_type": "product", "expected_leaks": 0},
    {"domain": "reddit.com", "category": "forum", "site_type": "thread", "expected_leaks": 0}
  ],
  "updated": "2026-07-10T00:00:00Z"
}
