{
  "timestamp": "2026-05-20T19:10:43.891265",
  "total_pages": 40,
  "total_em_dash_removed": 344,
  "total_brand_cleaned": 86,
  "total_rules_updated": 0,
  "total_149kb_removed": 0,
  "languages": [
    {
      "language": "en",
      "pages_processed": 4,
      "pages_failed": 0,
      "total_em_dash": 29,
      "total_brand_cleaned": 17,
      "total_rules_updated": 0,
      "total_149kb": 0,
      "files": [
        {
          "name": "terms.html",
          "em_dash": 4,
          "brand_cleaned": 5,
          "rules_updated": 0,
          "149kb": 0
        },
        {
          "name": "guide.html",
          "em_dash": 2,
          "brand_cleaned": 2,
          "rules_updated": 0,
          "149kb": 0
        },
        {
          "name": "privacy.html",
          "em_dash": 21,
          "brand_cleaned": 10,
          "rules_updated": 0,
          "149kb": 0
        },
        {
          "name": "withdrawal.html",
          "em_dash": 2,
          "brand_cleaned": 0,
          "rules_updated": 0,
          "149kb": 0
        }
      ]
    },
    {
      "language": "de",
      "pages_processed": 9,
      "pages_failed": 0,
      "total_em_dash": 64,
      "total_brand_cleaned": 17,
      "total_rules_updated": 0,
      "total_149kb": 0,
      "files": [
        {
          "name": "best-ad-blocker-2026.html",
          "em_dash": 6,
          "brand_cleaned": 1,
          "rules_updated": 0,
          "149kb": 0
        },
        {
          "name": "how-it-works.html",
          "em_dash": 9,
          "brand_cleaned": 0,
          "rules_updated": 0,
          "149kb": 0
        },
        {
          "name": "community.html",
          "em_dash": 1,
          "brand_cleaned": 1,
          "rules_updated": 0,
          "149kb": 0
        },
        {
          "name": "terms.html",
          "em_dash": 4,
          "brand_cleaned": 3,
          "rules_updated": 0,
          "149kb": 0
        },
        {
          "name": "guide.html",
          "em_dash": 3,
          "brand_cleaned": 1,
          "rules_updated": 0,
          "149kb": 0
        },
        {
          "name": "press.html",
          "em_dash": 16,
          "brand_cleaned": 1,
          "rules_updated": 0,
          "149kb": 0
        },
        {
          "name": "unique-tech.html",
          "em_dash": 5,
          "brand_cleaned": 0,
          "rules_updated": 0,
          "149kb": 0
        },
        {
          "name": "privacy.html",
          "em_dash": 20,
          "brand_cleaned": 10,
          "rules_updated": 0,
          "149kb": 0
        },
        {
          "name": "withdrawal.html",
          "em_dash": 0,
          "brand_cleaned": 0,
          "rules_updated": 0,
          "149kb": 0
        }
      ]
    },
    {
      "language": "fr",
      "pages_processed": 9,
      "pages_failed": 0,
      "total_em_dash": 83,
      "total_brand_cleaned": 18,
      "total_rules_updated": 0,
      "total_149kb": 0,
      "files": [
        {
          "name": "best-ad-blocker-2026.html",
          "em_dash": 14,
          "brand_cleaned": 1,
          "rules_updated": 0,
          "149kb": 0
        },
        {
          "name": "how-it-works.html",
          "em_dash": 13,
          "brand_cleaned": 1,
          "rules_updated": 0,
          "149kb": 0
        },
        {
          "name": "community.html",
          "em_dash": 6,
          "brand_cleaned": 1,
          "rules_updated": 0,
          "149kb": 0
        },
        {
          "name": "terms.html",
          "em_dash": 4,
          "brand_cleaned": 3,
          "rules_updated": 0,
          "149kb": 0
        },
        {
          "name": "guide.html",
          "em_dash": 3,
          "brand_cleaned": 1,
          "rules_updated": 0,
          "149kb": 0
        },
        {
          "name": "press.html",
          "em_dash": 18,
          "brand_cleaned": 1,
          "rules_updated": 0,
          "149kb": 0
        },
        {
          "name": "unique-tech.html",
          "em_dash": 5,
          "brand_cleaned": 0,
          "rules_updated": 0,
          "149kb": 0
        },
        {
          "name": "privacy.html",
          "em_dash": 20,
          "brand_cleaned": 10,
          "rules_updated": 0,
          "149kb": 0
        },
        {
          "name": "withdrawal.html",
          "em_dash": 0,
          "brand_cleaned": 0,
          "rules_updated": 0,
          "149kb": 0
        }
      ]
    },
    {
      "language": "es",
      "pages_processed": 9,
      "pages_failed": 0,
      "total_em_dash": 85,
      "total_brand_cleaned": 17,
      "total_rules_updated": 0,
      "total_149kb": 0,
      "files": [
        {
          "name": "best-ad-blocker-2026.html",
          "em_dash": 14,
          "brand_cleaned": 0,
          "rules_updated": 0,
          "149kb": 0
        },
        {
          "name": "how-it-works.html",
          "em_dash": 13,
          "brand_cleaned": 1,
          "rules_updated": 0,
          "149kb": 0
        },
        {
          "name": "community.html",
          "em_dash": 6,
          "brand_cleaned": 1,
          "rules_updated": 0,
          "149kb": 0
        },
        {
          "name": "terms.html",
          "em_dash": 4,
          "brand_cleaned": 3,
          "rules_updated": 0,
          "149kb": 0
        },
        {
          "name": "guide.html",
          "em_dash": 3,
          "brand_cleaned": 1,
          "rules_updated": 0,
          "149kb": 0
        },
        {
          "name": "press.html",
          "em_dash": 20,
          "brand_cleaned": 1,
          "rules_updated": 0,
          "149kb": 0
        },
        {
          "name": "unique-tech.html",
          "em_dash": 5,
          "brand_cleaned": 0,
          "rules_updated": 0,
          "149kb": 0
        },
        {
          "name": "privacy.html",
          "em_dash": 20,
          "brand_cleaned": 10,
          "rules_updated": 0,
          "149kb": 0
        },
        {
          "name": "withdrawal.html",
          "em_dash": 0,
          "brand_cleaned": 0,
          "rules_updated": 0,
          "149kb": 0
        }
      ]
    },
    {
      "language": "pt",
      "pages_processed": 9,
      "pages_failed": 0,
      "total_em_dash": 83,
      "total_brand_cleaned": 17,
      "total_rules_updated": 0,
      "total_149kb": 0,
      "files": [
        {
          "name": "best-ad-blocker-2026.html",
          "em_dash": 14,
          "brand_cleaned": 0,
          "rules_updated": 0,
          "149kb": 0
        },
        {
          "name": "how-it-works.html",
          "em_dash": 13,
          "brand_cleaned": 1,
          "rules_updated": 0,
          "149kb": 0
        },
        {
          "name": "community.html",
          "em_dash": 6,
          "brand_cleaned": 1,
          "rules_updated": 0,
          "149kb": 0
        },
        {
          "name": "terms.html",
          "em_dash": 4,
          "brand_cleaned": 3,
          "rules_updated": 0,
          "149kb": 0
        },
        {
          "name": "guide.html",
          "em_dash": 3,
          "brand_cleaned": 1,
          "rules_updated": 0,
          "149kb": 0
        },
        {
          "name": "press.html",
          "em_dash": 18,
          "brand_cleaned": 1,
          "rules_updated": 0,
          "149kb": 0
        },
        {
          "name": "unique-tech.html",
          "em_dash": 5,
          "brand_cleaned": 0,
          "rules_updated": 0,
          "149kb": 0
        },
        {
          "name": "privacy.html",
          "em_dash": 20,
          "brand_cleaned": 10,
          "rules_updated": 0,
          "149kb": 0
        },
        {
          "name": "withdrawal.html",
          "em_dash": 0,
          "brand_cleaned": 0,
          "rules_updated": 0,
          "149kb": 0
        }
      ]
    }
  ],
  "errors": []
}