{
  "version": "1.0.0",
  "updated": "2026-05-15",
  "brand": {
    "name": "AdOff",
    "tagline_en": "Ads? Off.",
    "tagline_it": "Pubblicita'? Spenta.",
    "domain": "adoff.app",
    "mission_en": "Universal ad blocker with stealth anti-detection. Invisible to anti-adblock walls. Privacy-first, zero tracking.",
    "mission_it": "Ad blocker universale con stealth anti-detection. Invisibile ai sistemi anti-adblock. Privacy-first, zero tracking.",
    "founded": "2026-04",
    "browsers_supported": ["Chrome", "Firefox", "Safari", "Edge", "Opera"],
    "pricing_eur": {
      "free_trial_days": 30,
      "monthly": 2.99,
      "annual_founder": 19.99,
      "annual_standard": 24.99,
      "lifetime_founder": 99
    }
  },
  "voice": {
    "tone_keywords": ["confident", "direct", "privacy-first", "minimal", "no fluff", "results-focused"],
    "tone_avoid": ["pushy", "hyperbolic", "tech-bro", "fear-mongering", "salesy"],
    "register": "casual-professional",
    "humor": "dry, subtle, never cringe",
    "perspective": "we (team voice) for product, you (direct) for user",
    "sentence_length_pref": "short to medium, one idea per sentence",
    "emoji_policy": "1-2 max per post, only when adds value (🛡️ ✅ ❌ ⚡ 🔒)"
  },
  "vocabulary": {
    "use": [
      "block", "stealth", "invisible", "privacy", "zero tracking",
      "anti-detection", "off", "clean", "fast", "universal",
      "no data collection", "free trial", "open source rules"
    ],
    "avoid_competitor_brand_names": true,
    "competitor_alternatives": {
      "uBlock Origin": "other ad blockers",
      "AdBlock Plus": "ad blocker incumbents",
      "Ghostery": "tracking blockers"
    },
    "platform_alternatives": {
      "YouTube": "video platforms",
      "Facebook": "social networks",
      "Instagram": "social media",
      "Twitter": "microblogging platforms",
      "Reddit": "community platforms",
      "Twitch": "live streaming platforms",
      "TikTok": "short-form video platforms",
      "Amazon": "e-commerce sites",
      "Google": "search engines"
    },
    "never_say": [
      "100% ad-free",
      "guarantee",
      "best in the world",
      "kill ads",
      "destroy advertisers"
    ],
    "official_claims_safe": [
      "blocks 130+ ad networks",
      "stealth anti-detection",
      "works on Chrome, Firefox, Safari, Edge, Opera",
      "30-day free Pro trial",
      "zero data collection",
      "stops video ads invisible to anti-adblock walls"
    ]
  },
  "visual": {
    "colors": {
      "deep_space": "#0a0a1a",
      "shield_purple": "#7c5cfc",
      "pure_white": "#ffffff",
      "midnight_blue": "#12122a",
      "steel_gray": "#8a8aaa",
      "soft_purple": "#b8a9ff",
      "success_green": "#4ade80",
      "alert_red": "#f43f5e"
    },
    "primary_gradient": "linear-gradient(135deg, #7c5cfc 0%, #4c3ad4 100%)",
    "typography": {
      "primary_font": "Inter",
      "mono_font": "JetBrains Mono",
      "weights": [400, 500, 600, 700]
    },
    "imagery_style": "minimal, dark-mode-first, geometric, no stock photos, no people faces, no flashy colors",
    "logo_assets": [
      "sviluppo/brand/assets/logo-512.png",
      "sviluppo/brand/assets/logo-512-transparent.png",
      "site/assets/logo.svg"
    ]
  },
  "personas": [
    {
      "id": "privacy_advocate",
      "name": "Privacy Advocate",
      "weight": 0.30,
      "tone": "serious, fact-driven, slightly idealistic",
      "interests": ["GDPR", "data rights", "surveillance capitalism", "open source"],
      "vocabulary_bias": ["tracking", "surveillance", "rights", "control", "harvest"],
      "hashtags": ["#privacy", "#surveillance", "#datarights", "#fediverse"],
      "example_hook": "Your browser sends 3,000+ tracking requests per day. Most go to companies you've never heard of.",
      "platforms": ["mastodon", "twitter", "reddit"]
    },
    {
      "id": "tech_geek",
      "name": "Tech Geek",
      "weight": 0.25,
      "tone": "casual, technical, slightly nerdy",
      "interests": ["browser internals", "MV3", "anti-fingerprinting", "WebAPI", "DevTools"],
      "vocabulary_bias": ["declarativeNetRequest", "MV3", "stealth", "hooks", "isolated world"],
      "hashtags": ["#webdev", "#privacy", "#browserextension", "#FOSS"],
      "example_hook": "MV3 broke a lot of ad blockers. We rebuilt the entire approach with declarativeNetRequest + IMA SDK stub.",
      "platforms": ["twitter", "reddit", "hackernews"]
    },
    {
      "id": "average_user",
      "name": "Average User",
      "weight": 0.30,
      "tone": "relatable, friendly, zero jargon",
      "interests": ["faster browsing", "less annoyance", "battery life", "kids safety"],
      "vocabulary_bias": ["annoying", "fast", "clean", "simple", "just works"],
      "hashtags": ["#ads", "#cleanbrowsing", "#privacy"],
      "example_hook": "Tired of watching 30-second video ads before every 2-minute clip?",
      "platforms": ["reddit", "mastodon"]
    },
    {
      "id": "founder_perspective",
      "name": "Founder Perspective",
      "weight": 0.15,
      "tone": "transparent, building-in-public, business-aware",
      "interests": ["bootstrapping", "indie SaaS", "user feedback", "honest pricing"],
      "vocabulary_bias": ["building", "shipping", "users", "feedback", "honest"],
      "hashtags": ["#buildinpublic", "#indiehacker", "#SaaS", "#privacy"],
      "example_hook": "We launched 2 months ago. 1,200 users. Zero ads. Here's what we learned.",
      "platforms": ["twitter", "mastodon", "indiehackers"]
    }
  ],
  "formats": {
    "twitter": {
      "max_chars": 280,
      "hashtag_count_max": 2,
      "emoji_count_max": 2,
      "include_cta_pct": 0.4,
      "thread_format_pct": 0.1
    },
    "mastodon": {
      "max_chars": 500,
      "hashtag_count_max": 3,
      "emoji_count_max": 3,
      "include_cta_pct": 0.5,
      "thread_format_pct": 0.2
    },
    "reddit": {
      "max_chars": 1500,
      "hashtag_count_max": 0,
      "emoji_count_max": 0,
      "include_cta_pct": 0.1,
      "tone_shift": "more authentic, less promotional, no link without context",
      "anti_promotional_rule": "Reddit hates ads. Never start with brand. Always provide value first."
    },
    "blog_post": {
      "target_words": 1500,
      "structure": "hook, problem, agitate, solution, evidence, CTA",
      "seo_keyword_density_pct": 1.5,
      "internal_links_min": 3
    },
    "press_email": {
      "max_words": 80,
      "structure": "personalized hook (1 line) + 1 specific reason for THEIR audience + soft CTA",
      "subject_max_chars": 60,
      "no_signature_emoji": true
    },
    "quora_answer": {
      "max_words": 400,
      "structure": "direct answer first, then context, then product mention (only if relevant)",
      "soft_promotion": true
    }
  },
  "frameworks": {
    "PAS": {
      "stages": ["Problem", "Agitate", "Solution"],
      "best_for": ["video ads pain", "tracking pain", "speed pain"],
      "platforms": ["twitter", "mastodon", "reddit", "blog"]
    },
    "AIDA": {
      "stages": ["Attention", "Interest", "Desire", "Action"],
      "best_for": ["press release", "blog hero", "landing page hooks"],
      "platforms": ["blog", "press_email"]
    },
    "FAB": {
      "stages": ["Feature", "Advantage", "Benefit"],
      "best_for": ["technical announcements", "MV3 deep dives", "stealth mechanism"],
      "platforms": ["reddit", "hackernews", "blog"]
    },
    "hook_story_offer": {
      "stages": ["Hook (1 line)", "Story (3-5 lines)", "Offer (1 line)"],
      "best_for": ["building-in-public posts", "user testimonials", "milestones"],
      "platforms": ["twitter", "mastodon"]
    }
  },
  "compliance": {
    "never_in_marketing_output": [
      "founder real name",
      "founder personal email",
      "founder city",
      "tax id / VAT number",
      "Stripe internal IDs",
      "Cloudflare account email"
    ],
    "domain_whitelist": [
      "https://adoff.app",
      "https://adoff.app/install",
      "https://adoff.app/support",
      "https://adoff.app/privacy",
      "https://adoff.app/affiliati"
    ],
    "regulatory_safe_claims": [
      "We do not collect personal data",
      "We do not track users",
      "We do not sell data",
      "Network rules are publicly auditable"
    ]
  },
  "anti_repetition": {
    "phrase_cooldown_days": 14,
    "hook_variety_min": 8,
    "persona_rotation": "round-robin weighted by persona.weight",
    "temperature_schedule": {
      "hook_generation": 1.0,
      "body_generation": 0.7,
      "cta_generation": 0.4,
      "validation_check": 0.2
    }
  },
  "few_shot_examples": [
    {
      "platform": "twitter",
      "persona": "privacy_advocate",
      "framework": "PAS",
      "text": "Most ad blockers fail on video platforms. Anti-adblock walls detect them in seconds.\n\nAdOff doesn't get detected. We rebuilt blocking from scratch with MV3 + stealth IMA stub.\n\n30 days free Pro. No card. adoff.app",
      "performance_note": "concrete tech detail + clear differentiator + no-friction CTA"
    },
    {
      "platform": "mastodon",
      "persona": "tech_geek",
      "framework": "FAB",
      "text": "Quick MV3 ad blocker deep dive 🛡️\n\nManifest V3 killed dynamic rule injection. Most blockers downgraded.\n\nWe built around declarativeNetRequest with 130+ rules + an IMA SDK stub that emits CONTENT_RESUME_REQUESTED. Zero detection on video platforms.\n\nFOSS rules. Source visible.\n\nadoff.app",
      "performance_note": "specific MV3 terminology + technical novelty + FOSS angle"
    },
    {
      "platform": "reddit",
      "persona": "average_user",
      "framework": "PAS",
      "text": "I was watching a 90-second video tutorial yesterday. Pre-roll: 35 seconds. Mid-roll: 20 seconds. Total wasted: 55 seconds on 90 of content.\n\nThat's 38% of my time spent on ads.\n\nI'm a regular user, not a privacy nerd. I just want to watch the thing I clicked on. Found AdOff last week, blocks all of them including the anti-adblock walls that pop up on some sites. Free trial gave me 30 days, decided to keep it.\n\nAnyone else hitting the wall on ad fatigue these days?",
      "performance_note": "personal story, concrete numbers, no upfront brand push, ends as discussion"
    }
  ]
}
